firm/README.md
firm/__init__.py
firm/_calibration.py
firm/_constants.py
firm/_firm.py
firm/_packets.py
firm/py.typed
firm_hprc-0.2.0.dist-info/WHEEL
firm_hprc-0.2.0.dist-info/METADATA
firm_hprc-0.2.0.dist-info/RECORD
