Metadata-Version: 2.4
Name: firm-hprc
Version: 0.2.0
Summary: Filtered Inertial Rotation Module
Keywords: firm,flight computer,python,rocketry
Author: High Powered Rocketry Club
Author-email: High Powered Rocketry Club <ncsurocketry@gmail.com>
License-Expression: MIT
Classifier: Development Status :: 4 - Beta
Classifier: Topic :: Software Development :: Libraries :: Python Modules
Classifier: Operating System :: OS Independent
Classifier: Programming Language :: Python
Classifier: Programming Language :: Python :: 3
Classifier: Programming Language :: Python :: 3.10
Classifier: Programming Language :: Python :: 3.11
Classifier: Programming Language :: Python :: 3.12
Classifier: Programming Language :: Python :: 3.13
Requires-Dist: msgspec>=0.19.0
Requires-Dist: pyserial>=3.5
Requires-Python: >=3.10, <3.14
Project-URL: Bug Tracker, https://github.com/NCSU-High-Powered-Rocketry-Club/FIRM/issues
Project-URL: Homepage, https://ncsurocketry.org
Project-URL: Source Code, https://github.com/NCSU-High-Powered-Rocketry-Club/FIRM/
